{  "type": "Text Layer Properties",  "verifiedDate": "2026-04-03",  "verifiedAEVersion": "26.0x67",  "textProperties": {    "name": "Source Text",    "matchName": "ADBE Text Document",    "valueType": "TEXT_DOCUMENT",    "defaultValue": {      "text": "Sample",      "font": "Inter-Light",      "fontSize": 41.3300018310547,      "applyFill": true,      "applyStroke": false,      "justification": "7413"    }  },  "pathOptions": {    "name": "Path Options",    "matchName": "ADBE Text Path Options",    "type": "group",    "numProperties": 6,    "children": [      {        "name": "Path",        "matchName": "ADBE Text Path",        "valueType": "MASK_INDEX",        "defaultValue": 0      },      {        "name": "Reverse Path",        "matchName": "ADBE Text Reverse Path",        "valueType": "OneD",        "defaultValue": 0      },      {        "name": "Perpendicular To Path",        "matchName": "ADBE Text Perpendicular To Path",        "valueType": "OneD",        "defaultValue": 1      },      {        "name": "Force Alignment",        "matchName": "ADBE Text Force Align Path",        "valueType": "OneD",        "defaultValue": 0      },      {        "name": "First Margin",        "matchName": "ADBE Text First Margin",        "valueType": "OneD",        "defaultValue": 0      },      {        "name": "Last Margin",        "matchName": "ADBE Text Last Margin",        "valueType": "OneD",        "defaultValue": 0      }    ]  },  "moreOptions": {    "name": "More Options",    "matchName": "ADBE Text More Options",    "type": "group",    "numProperties": 5,    "children": [      {        "name": "Anchor Point Grouping",        "matchName": "ADBE Text Anchor Point Option",        "valueType": "OneD",        "defaultValue": 1      },      {        "name": "Grouping Alignment",        "matchName": "ADBE Text Anchor Point Align",        "valueType": "TwoD",        "defaultValue": [          0,          0        ]      },      {        "name": "Fill & Stroke",        "matchName": "ADBE Text Render Order",        "valueType": "OneD",        "defaultValue": 1      },      {        "name": "Inter-Character Blending",        "matchName": "ADBE Text Character Blend Mode",        "valueType": "OneD",        "defaultValue": 1      },      {        "name": "Variable Font Spacing",        "matchName": "ADBE Text Variable Font Spacing",        "valueType": "OneD",        "defaultValue": 1      }    ]  },  "animator": {    "name": "Discovery Animator",    "matchName": "ADBE Text Animator",    "type": "group",    "numProperties": 2,    "children": [      {        "name": "Selectors",        "matchName": "ADBE Text Selectors",        "type": "group",        "numProperties": 0,        "children": [                  ]      },      {        "name": "Properties",        "matchName": "ADBE Text Animator Properties",        "type": "group",        "numProperties": 103,        "children": [          {            "name": "Anchor Point",            "matchName": "ADBE Text Anchor Point 3D",            "valueType": "ThreeD_SPATIAL",            "defaultValue": [              0,              0,              0            ]          },          {            "name": "Position",            "matchName": "ADBE Text Position 3D",            "valueType": "ThreeD_SPATIAL",            "defaultValue": [              0,              0,              0            ]          },          {            "name": "Scale",            "matchName": "ADBE Text Scale 3D",            "valueType": "ThreeD",            "defaultValue": [              100,              100,              100            ]          },          {            "name": "Skew",            "matchName": "ADBE Text Skew",            "valueType": "OneD",            "defaultValue": 0          },          {            "name": "Skew Axis",            "matchName": "ADBE Text Skew Axis",            "valueType": "OneD",            "defaultValue": 0          },          {            "name": "X Rotation",            "matchName": "ADBE Text Rotation X",            "valueType": "OneD",            "defaultValue": 0          },          {            "name": "Y Rotation",            "matchName": "ADBE Text Rotation Y",            "valueType": "OneD",            "defaultValue": 0          },          {            "name": "Rotation",            "matchName": "ADBE Text Rotation",            "valueType": "OneD",            "defaultValue": 0          },          {            "name": "Opacity",            "matchName": "ADBE Text Opacity",            "valueType": "OneD",            "defaultValue": 100          },          {            "name": "Fill Opacity",            "matchName": "ADBE Text Fill Opacity",            "valueType": "OneD",            "defaultValue": 100          },          {            "name": "Stroke Opacity",            "matchName": "ADBE Text Stroke Opacity",            "valueType": "OneD",            "defaultValue": 100          },          {            "name": "Fill Color",            "matchName": "ADBE Text Fill Color",            "valueType": "COLOR",            "defaultValue": [              1,              0,              0,              1            ]          },          {            "name": "Stroke Color",            "matchName": "ADBE Text Stroke Color",            "valueType": "COLOR",            "defaultValue": [              1,              0,              0,              1            ]          },          {            "name": "Fill Hue",            "matchName": "ADBE Text Fill Hue",            "valueType": "OneD",            "defaultValue": 0          },          {            "name": "Stroke Hue",            "matchName": "ADBE Text Stroke Hue",            "valueType": "OneD",            "defaultValue": 0          },          {            "name": "Fill Saturation",            "matchName": "ADBE Text Fill Saturation",            "valueType": "OneD",            "defaultValue": 0          },          {            "name": "Stroke Saturation",            "matchName": "ADBE Text Stroke Saturation",            "valueType": "OneD",            "defaultValue": 0          },          {            "name": "Fill Brightness",            "matchName": "ADBE Text Fill Brightness",            "valueType": "OneD",            "defaultValue": 0          },          {            "name": "Stroke Brightness",            "matchName": "ADBE Text Stroke Brightness",            "valueType": "OneD",            "defaultValue": 0          },          {            "name": "Front Color",            "matchName": "ADBE 3DText Front RGB",            "valueType": "COLOR",            "defaultValue": [              1,              0,              0,              1            ]          },          {            "name": "Front Hue",            "matchName": "ADBE 3DText Front Hue",            "valueType": "OneD",            "defaultValue": 0          },          {            "name": "Front Saturation",            "matchName": "ADBE 3DText Front Sat",            "valueType": "OneD",            "defaultValue": 0          },          {            "name": "Front Brightness",            "matchName": "ADBE 3DText Front Bright",            "valueType": "OneD",            "defaultValue": 0          },          {            "name": "Front Opacity",            "matchName": "ADBE 3DText Front Opacity",            "valueType": "OneD",            "defaultValue": 100          },          {            "name": "Front Ambient",            "matchName": "ADBE 3DText Front Ambient",            "valueType": "OneD",            "defaultValue": 100          },          {            "name": "Front Diffuse",            "matchName": "ADBE 3DText Front Diffuse",            "valueType": "OneD",            "defaultValue": 50          },          {            "name": "Front Specular Intensity",            "matchName": "ADBE 3DText Front Specular",            "valueType": "OneD",            "defaultValue": 50          },          {            "name": "Front Specular Shininess",            "matchName": "ADBE 3DText Front Shininess",            "valueType": "OneD",            "defaultValue": 5          },          {            "name": "Front Metal",            "matchName": "ADBE 3DText Front Metal",            "valueType": "OneD",            "defaultValue": 100          },          {            "name": "Front Reflection Intensity",            "matchName": "ADBE 3DText Front Reflection",            "valueType": "OneD",            "defaultValue": 0          },          {            "name": "Front Reflection Sharpness",            "matchName": "ADBE 3DText Front Gloss",            "valueType": "OneD",            "defaultValue": 100          },          {            "name": "Front Reflection Rolloff",            "matchName": "ADBE 3DText Front Fresnel",            "valueType": "OneD",            "defaultValue": 0          },          {            "name": "Front Transparency",            "matchName": "ADBE 3DText Front Xparency",            "valueType": "OneD",            "defaultValue": 0          },          {            "name": "Front Transparency Rolloff",            "matchName": "ADBE 3DText Front XparRoll",            "valueType": "OneD",            "defaultValue": 0          },          {            "name": "Front Index of Refraction",            "matchName": "ADBE 3DText Front IOR",            "valueType": "OneD",            "defaultValue": 1          },          {            "name": "Bevel Color",            "matchName": "ADBE 3DText Bevel RGB",            "valueType": "COLOR",            "defaultValue": [              1,              0,              0,              1            ]          },          {            "name": "Bevel Hue",            "matchName": "ADBE 3DText Bevel Hue",            "valueType": "OneD",            "defaultValue": 0          },          {            "name": "Bevel Saturation",            "matchName": "ADBE 3DText Bevel Sat",            "valueType": "OneD",            "defaultValue": 0          },          {            "name": "Bevel Brightness",            "matchName": "ADBE 3DText Bevel Bright",            "valueType": "OneD",            "defaultValue": 0          },          {            "name": "Bevel Opacity",            "matchName": "ADBE 3DText Bevel Opacity",            "valueType": "OneD",            "defaultValue": 100          },          {            "name": "Bevel Ambient",            "matchName": "ADBE 3DText Bevel Ambient",            "valueType": "OneD",            "defaultValue": 100          },          {            "name": "Bevel Diffuse",            "matchName": "ADBE 3DText Bevel Diffuse",            "valueType": "OneD",            "defaultValue": 50          },          {            "name": "Bevel Specular Intensity",            "matchName": "ADBE 3DText Bevel Specular",            "valueType": "OneD",            "defaultValue": 50          },          {            "name": "Bevel Specular Shininess",            "matchName": "ADBE 3DText Bevel Shininess",            "valueType": "OneD",            "defaultValue": 5          },          {            "name": "Bevel Metal",            "matchName": "ADBE 3DText Bevel Metal",            "valueType": "OneD",            "defaultValue": 100          },          {            "name": "Bevel Reflection Intensity",            "matchName": "ADBE 3DText Bevel Reflection",            "valueType": "OneD",            "defaultValue": 0          },          {            "name": "Bevel Reflection Sharpness",            "matchName": "ADBE 3DText Bevel Gloss",            "valueType": "OneD",            "defaultValue": 100          },          {            "name": "Bevel Reflection Rolloff",            "matchName": "ADBE 3DText Bevel Fresnel",            "valueType": "OneD",            "defaultValue": 0          },          {            "name": "Bevel Transparency",            "matchName": "ADBE 3DText Bevel Xparency",            "valueType": "OneD",            "defaultValue": 0          },          {            "name": "Bevel Transparency Rolloff",            "matchName": "ADBE 3DText Bevel XparRoll",            "valueType": "OneD",            "defaultValue": 0          },          {            "name": "Bevel Index of Refraction",            "matchName": "ADBE 3DText Bevel IOR",            "valueType": "OneD",            "defaultValue": 1          },          {            "name": "Side Color",            "matchName": "ADBE 3DText Side RGB",            "valueType": "COLOR",            "defaultValue": [              1,              0,              0,              1            ]          },          {            "name": "Side Hue",            "matchName": "ADBE 3DText Side Hue",            "valueType": "OneD",            "defaultValue": 0          },          {            "name": "Side Saturation",            "matchName": "ADBE 3DText Side Sat",            "valueType": "OneD",            "defaultValue": 0          },          {            "name": "Side Brightness",            "matchName": "ADBE 3DText Side Bright",            "valueType": "OneD",            "defaultValue": 0          },          {            "name": "Side Opacity",            "matchName": "ADBE 3DText Side Opacity",            "valueType": "OneD",            "defaultValue": 100          },          {            "name": "Side Ambient",            "matchName": "ADBE 3DText Side Ambient",            "valueType": "OneD",            "defaultValue": 100          },          {            "name": "Side Diffuse",            "matchName": "ADBE 3DText Side Diffuse",            "valueType": "OneD",            "defaultValue": 50          },          {            "name": "Side Specular Intensity",            "matchName": "ADBE 3DText Side Specular",            "valueType": "OneD",            "defaultValue": 50          },          {            "name": "Side Specular Shininess",            "matchName": "ADBE 3DText Side Shininess",            "valueType": "OneD",            "defaultValue": 5          },          {            "name": "Side Metal",            "matchName": "ADBE 3DText Side Metal",            "valueType": "OneD",            "defaultValue": 100          },          {            "name": "Side Reflection Intensity",            "matchName": "ADBE 3DText Side Reflection",            "valueType": "OneD",            "defaultValue": 0          },          {            "name": "Side Reflection Sharpness",            "matchName": "ADBE 3DText Side Gloss",            "valueType": "OneD",            "defaultValue": 100          },          {            "name": "Side Reflection Rolloff",            "matchName": "ADBE 3DText Side Fresnel",            "valueType": "OneD",            "defaultValue": 0          },          {            "name": "Side Transparency",            "matchName": "ADBE 3DText Side Xparency",            "valueType": "OneD",            "defaultValue": 0          },          {            "name": "Side Transparency Rolloff",            "matchName": "ADBE 3DText Side XparRoll",            "valueType": "OneD",            "defaultValue": 0          },          {            "name": "Side Index of Refraction",            "matchName": "ADBE 3DText Side IOR",            "valueType": "OneD",            "defaultValue": 1          },          {            "name": "Back Color",            "matchName": "ADBE 3DText Back RGB",            "valueType": "COLOR",            "defaultValue": [              1,              0,              0,              1            ]          },          {            "name": "Back Hue",            "matchName": "ADBE 3DText Back Hue",            "valueType": "OneD",            "defaultValue": 0          },          {            "name": "Back Saturation",            "matchName": "ADBE 3DText Back Sat",            "valueType": "OneD",            "defaultValue": 0          },          {            "name": "Back Brightness",            "matchName": "ADBE 3DText Back Bright",            "valueType": "OneD",            "defaultValue": 0          },          {            "name": "Back Opacity",            "matchName": "ADBE 3DText Back Opacity",            "valueType": "OneD",            "defaultValue": 100          },          {            "name": "Back Ambient",            "matchName": "ADBE 3DText Back Ambient",            "valueType": "OneD",            "defaultValue": 100          },          {            "name": "Back Diffuse",            "matchName": "ADBE 3DText Back Diffuse",            "valueType": "OneD",            "defaultValue": 50          },          {            "name": "Back Specular Intensity",            "matchName": "ADBE 3DText Back Specular",            "valueType": "OneD",            "defaultValue": 50          },          {            "name": "Back Specular Shininess",            "matchName": "ADBE 3DText Back Shininess",            "valueType": "OneD",            "defaultValue": 5          },          {            "name": "Back Metal",            "matchName": "ADBE 3DText Back Metal",            "valueType": "OneD",            "defaultValue": 100          },          {            "name": "Back Reflection Intensity",            "matchName": "ADBE 3DText Back Reflection",            "valueType": "OneD",            "defaultValue": 0          },          {            "name": "Back Reflection Sharpness",            "matchName": "ADBE 3DText Back Gloss",            "valueType": "OneD",            "defaultValue": 100          },          {            "name": "Back Reflection Rolloff",            "matchName": "ADBE 3DText Back Fresnel",            "valueType": "OneD",            "defaultValue": 0          },          {            "name": "Back Transparency",            "matchName": "ADBE 3DText Back Xparency",            "valueType": "OneD",            "defaultValue": 0          },          {            "name": "Back Transparency Rolloff",            "matchName": "ADBE 3DText Back XparRoll",            "valueType": "OneD",            "defaultValue": 0          },          {            "name": "Back Index of Refraction",            "matchName": "ADBE 3DText Back IOR",            "valueType": "OneD",            "defaultValue": 1          },          {            "name": "Bevel Depth",            "matchName": "ADBE 3DText Bevel Depth",            "valueType": "OneD",            "defaultValue": 2          },          {            "name": "Extrusion Depth",            "matchName": "ADBE 3DText Extrude Depth",            "valueType": "OneD",            "defaultValue": 0          },          {            "name": "Stroke Width",            "matchName": "ADBE Text Stroke Width",            "valueType": "OneD",            "defaultValue": 0          },          {            "name": "Line Anchor",            "matchName": "ADBE Text Line Anchor",            "valueType": "OneD",            "defaultValue": 50          },          {            "name": "Tracking Type",            "matchName": "ADBE Text Track Type",            "valueType": "OneD",            "defaultValue": 1          },          {            "name": "Tracking Amount",            "matchName": "ADBE Text Tracking Amount",            "valueType": "OneD",            "defaultValue": 0          },          {            "name": "Character Alignment",            "matchName": "ADBE Text Character Change Type",            "valueType": "OneD",            "defaultValue": 1          },          {            "name": "Character Range",            "matchName": "ADBE Text Character Range",            "valueType": "OneD",            "defaultValue": 1          },          {            "name": "Character Value",            "matchName": "ADBE Text Character Replace",            "valueType": "OneD",            "defaultValue": 0          },          {            "name": "Character Offset",            "matchName": "ADBE Text Character Offset",            "valueType": "OneD",            "defaultValue": 0          },          {            "name": "Line Spacing",            "matchName": "ADBE Text Line Spacing",            "valueType": "TwoD",            "defaultValue": [              0,              0            ]          },          {            "name": "Blur",            "matchName": "ADBE Text Blur",            "valueType": "TwoD",            "defaultValue": [              0,              0            ]          },          {            "name": "",            "matchName": "ADBE Text VF Axis 1",            "valueType": "UNKNOWN_161",            "defaultValue": 0          },          {            "name": "",            "matchName": "ADBE Text VF Axis 2",            "valueType": "UNKNOWN_161",            "defaultValue": 0          },          {            "name": "",            "matchName": "ADBE Text VF Axis 3",            "valueType": "UNKNOWN_161",            "defaultValue": 0          },          {            "name": "",            "matchName": "ADBE Text VF Axis 4",            "valueType": "UNKNOWN_161",            "defaultValue": 0          },          {            "name": "",            "matchName": "ADBE Text VF Axis 5",            "valueType": "UNKNOWN_161",            "defaultValue": 0          },          {            "name": "",            "matchName": "ADBE Text VF Axis 6",            "valueType": "UNKNOWN_161",            "defaultValue": 0          },          {            "name": "",            "matchName": "ADBE Text VF Axis 7",            "valueType": "UNKNOWN_161",            "defaultValue": 0          },          {            "name": "",            "matchName": "ADBE Text VF Axis 8",            "valueType": "UNKNOWN_161",            "defaultValue": 0          }        ]      }    ]  },  "animatorProperties": {    "name": "Properties",    "matchName": "ADBE Text Animator Properties",    "type": "group",    "numProperties": 103,    "children": [      {        "name": "Anchor Point",        "matchName": "ADBE Text Anchor Point 3D",        "valueType": "ThreeD_SPATIAL",        "defaultValue": [          0,          0,          0        ]      },      {        "name": "Position",        "matchName": "ADBE Text Position 3D",        "valueType": "ThreeD_SPATIAL",        "defaultValue": [          0,          0,          0        ]      },      {        "name": "Scale",        "matchName": "ADBE Text Scale 3D",        "valueType": "ThreeD",        "defaultValue": [          100,          100,          100        ]      },      {        "name": "Skew",        "matchName": "ADBE Text Skew",        "valueType": "OneD",        "defaultValue": 0      },      {        "name": "Skew Axis",        "matchName": "ADBE Text Skew Axis",        "valueType": "OneD",        "defaultValue": 0      },      {        "name": "X Rotation",        "matchName": "ADBE Text Rotation X",        "valueType": "OneD",        "defaultValue": 0      },      {        "name": "Y Rotation",        "matchName": "ADBE Text Rotation Y",        "valueType": "OneD",        "defaultValue": 0      },      {        "name": "Rotation",        "matchName": "ADBE Text Rotation",        "valueType": "OneD",        "defaultValue": 0      },      {        "name": "Opacity",        "matchName": "ADBE Text Opacity",        "valueType": "OneD",        "defaultValue": 100      },      {        "name": "Fill Opacity",        "matchName": "ADBE Text Fill Opacity",        "valueType": "OneD",        "defaultValue": 100      },      {        "name": "Stroke Opacity",        "matchName": "ADBE Text Stroke Opacity",        "valueType": "OneD",        "defaultValue": 100      },      {        "name": "Fill Color",        "matchName": "ADBE Text Fill Color",        "valueType": "COLOR",        "defaultValue": [          1,          0,          0,          1        ]      },      {        "name": "Stroke Color",        "matchName": "ADBE Text Stroke Color",        "valueType": "COLOR",        "defaultValue": [          1,          0,          0,          1        ]      },      {        "name": "Fill Hue",        "matchName": "ADBE Text Fill Hue",        "valueType": "OneD",        "defaultValue": 0      },      {        "name": "Stroke Hue",        "matchName": "ADBE Text Stroke Hue",        "valueType": "OneD",        "defaultValue": 0      },      {        "name": "Fill Saturation",        "matchName": "ADBE Text Fill Saturation",        "valueType": "OneD",        "defaultValue": 0      },      {        "name": "Stroke Saturation",        "matchName": "ADBE Text Stroke Saturation",        "valueType": "OneD",        "defaultValue": 0      },      {        "name": "Fill Brightness",        "matchName": "ADBE Text Fill Brightness",        "valueType": "OneD",        "defaultValue": 0      },      {        "name": "Stroke Brightness",        "matchName": "ADBE Text Stroke Brightness",        "valueType": "OneD",        "defaultValue": 0      },      {        "name": "Front Color",        "matchName": "ADBE 3DText Front RGB",        "valueType": "COLOR",        "defaultValue": [          1,          0,          0,          1        ]      },      {        "name": "Front Hue",        "matchName": "ADBE 3DText Front Hue",        "valueType": "OneD",        "defaultValue": 0      },      {        "name": "Front Saturation",        "matchName": "ADBE 3DText Front Sat",        "valueType": "OneD",        "defaultValue": 0      },      {        "name": "Front Brightness",        "matchName": "ADBE 3DText Front Bright",        "valueType": "OneD",        "defaultValue": 0      },      {        "name": "Front Opacity",        "matchName": "ADBE 3DText Front Opacity",        "valueType": "OneD",        "defaultValue": 100      },      {        "name": "Front Ambient",        "matchName": "ADBE 3DText Front Ambient",        "valueType": "OneD",        "defaultValue": 100      },      {        "name": "Front Diffuse",        "matchName": "ADBE 3DText Front Diffuse",        "valueType": "OneD",        "defaultValue": 50      },      {        "name": "Front Specular Intensity",        "matchName": "ADBE 3DText Front Specular",        "valueType": "OneD",        "defaultValue": 50      },      {        "name": "Front Specular Shininess",        "matchName": "ADBE 3DText Front Shininess",        "valueType": "OneD",        "defaultValue": 5      },      {        "name": "Front Metal",        "matchName": "ADBE 3DText Front Metal",        "valueType": "OneD",        "defaultValue": 100      },      {        "name": "Front Reflection Intensity",        "matchName": "ADBE 3DText Front Reflection",        "valueType": "OneD",        "defaultValue": 0      },      {        "name": "Front Reflection Sharpness",        "matchName": "ADBE 3DText Front Gloss",        "valueType": "OneD",        "defaultValue": 100      },      {        "name": "Front Reflection Rolloff",        "matchName": "ADBE 3DText Front Fresnel",        "valueType": "OneD",        "defaultValue": 0      },      {        "name": "Front Transparency",        "matchName": "ADBE 3DText Front Xparency",        "valueType": "OneD",        "defaultValue": 0      },      {        "name": "Front Transparency Rolloff",        "matchName": "ADBE 3DText Front XparRoll",        "valueType": "OneD",        "defaultValue": 0      },      {        "name": "Front Index of Refraction",        "matchName": "ADBE 3DText Front IOR",        "valueType": "OneD",        "defaultValue": 1      },      {        "name": "Bevel Color",        "matchName": "ADBE 3DText Bevel RGB",        "valueType": "COLOR",        "defaultValue": [          1,          0,          0,          1        ]      },      {        "name": "Bevel Hue",        "matchName": "ADBE 3DText Bevel Hue",        "valueType": "OneD",        "defaultValue": 0      },      {        "name": "Bevel Saturation",        "matchName": "ADBE 3DText Bevel Sat",        "valueType": "OneD",        "defaultValue": 0      },      {        "name": "Bevel Brightness",        "matchName": "ADBE 3DText Bevel Bright",        "valueType": "OneD",        "defaultValue": 0      },      {        "name": "Bevel Opacity",        "matchName": "ADBE 3DText Bevel Opacity",        "valueType": "OneD",        "defaultValue": 100      },      {        "name": "Bevel Ambient",        "matchName": "ADBE 3DText Bevel Ambient",        "valueType": "OneD",        "defaultValue": 100      },      {        "name": "Bevel Diffuse",        "matchName": "ADBE 3DText Bevel Diffuse",        "valueType": "OneD",        "defaultValue": 50      },      {        "name": "Bevel Specular Intensity",        "matchName": "ADBE 3DText Bevel Specular",        "valueType": "OneD",        "defaultValue": 50      },      {        "name": "Bevel Specular Shininess",        "matchName": "ADBE 3DText Bevel Shininess",        "valueType": "OneD",        "defaultValue": 5      },      {        "name": "Bevel Metal",        "matchName": "ADBE 3DText Bevel Metal",        "valueType": "OneD",        "defaultValue": 100      },      {        "name": "Bevel Reflection Intensity",        "matchName": "ADBE 3DText Bevel Reflection",        "valueType": "OneD",        "defaultValue": 0      },      {        "name": "Bevel Reflection Sharpness",        "matchName": "ADBE 3DText Bevel Gloss",        "valueType": "OneD",        "defaultValue": 100      },      {        "name": "Bevel Reflection Rolloff",        "matchName": "ADBE 3DText Bevel Fresnel",        "valueType": "OneD",        "defaultValue": 0      },      {        "name": "Bevel Transparency",        "matchName": "ADBE 3DText Bevel Xparency",        "valueType": "OneD",        "defaultValue": 0      },      {        "name": "Bevel Transparency Rolloff",        "matchName": "ADBE 3DText Bevel XparRoll",        "valueType": "OneD",        "defaultValue": 0      },      {        "name": "Bevel Index of Refraction",        "matchName": "ADBE 3DText Bevel IOR",        "valueType": "OneD",        "defaultValue": 1      },      {        "name": "Side Color",        "matchName": "ADBE 3DText Side RGB",        "valueType": "COLOR",        "defaultValue": [          1,          0,          0,          1        ]      },      {        "name": "Side Hue",        "matchName": "ADBE 3DText Side Hue",        "valueType": "OneD",        "defaultValue": 0      },      {        "name": "Side Saturation",        "matchName": "ADBE 3DText Side Sat",        "valueType": "OneD",        "defaultValue": 0      },      {        "name": "Side Brightness",        "matchName": "ADBE 3DText Side Bright",        "valueType": "OneD",        "defaultValue": 0      },      {        "name": "Side Opacity",        "matchName": "ADBE 3DText Side Opacity",        "valueType": "OneD",        "defaultValue": 100      },      {        "name": "Side Ambient",        "matchName": "ADBE 3DText Side Ambient",        "valueType": "OneD",        "defaultValue": 100      },      {        "name": "Side Diffuse",        "matchName": "ADBE 3DText Side Diffuse",        "valueType": "OneD",        "defaultValue": 50      },      {        "name": "Side Specular Intensity",        "matchName": "ADBE 3DText Side Specular",        "valueType": "OneD",        "defaultValue": 50      },      {        "name": "Side Specular Shininess",        "matchName": "ADBE 3DText Side Shininess",        "valueType": "OneD",        "defaultValue": 5      },      {        "name": "Side Metal",        "matchName": "ADBE 3DText Side Metal",        "valueType": "OneD",        "defaultValue": 100      },      {        "name": "Side Reflection Intensity",        "matchName": "ADBE 3DText Side Reflection",        "valueType": "OneD",        "defaultValue": 0      },      {        "name": "Side Reflection Sharpness",        "matchName": "ADBE 3DText Side Gloss",        "valueType": "OneD",        "defaultValue": 100      },      {        "name": "Side Reflection Rolloff",        "matchName": "ADBE 3DText Side Fresnel",        "valueType": "OneD",        "defaultValue": 0      },      {        "name": "Side Transparency",        "matchName": "ADBE 3DText Side Xparency",        "valueType": "OneD",        "defaultValue": 0      },      {        "name": "Side Transparency Rolloff",        "matchName": "ADBE 3DText Side XparRoll",        "valueType": "OneD",        "defaultValue": 0      },      {        "name": "Side Index of Refraction",        "matchName": "ADBE 3DText Side IOR",        "valueType": "OneD",        "defaultValue": 1      },      {        "name": "Back Color",        "matchName": "ADBE 3DText Back RGB",        "valueType": "COLOR",        "defaultValue": [          1,          0,          0,          1        ]      },      {        "name": "Back Hue",        "matchName": "ADBE 3DText Back Hue",        "valueType": "OneD",        "defaultValue": 0      },      {        "name": "Back Saturation",        "matchName": "ADBE 3DText Back Sat",        "valueType": "OneD",        "defaultValue": 0      },      {        "name": "Back Brightness",        "matchName": "ADBE 3DText Back Bright",        "valueType": "OneD",        "defaultValue": 0      },      {        "name": "Back Opacity",        "matchName": "ADBE 3DText Back Opacity",        "valueType": "OneD",        "defaultValue": 100      },      {        "name": "Back Ambient",        "matchName": "ADBE 3DText Back Ambient",        "valueType": "OneD",        "defaultValue": 100      },      {        "name": "Back Diffuse",        "matchName": "ADBE 3DText Back Diffuse",        "valueType": "OneD",        "defaultValue": 50      },      {        "name": "Back Specular Intensity",        "matchName": "ADBE 3DText Back Specular",        "valueType": "OneD",        "defaultValue": 50      },      {        "name": "Back Specular Shininess",        "matchName": "ADBE 3DText Back Shininess",        "valueType": "OneD",        "defaultValue": 5      },      {        "name": "Back Metal",        "matchName": "ADBE 3DText Back Metal",        "valueType": "OneD",        "defaultValue": 100      },      {        "name": "Back Reflection Intensity",        "matchName": "ADBE 3DText Back Reflection",        "valueType": "OneD",        "defaultValue": 0      },      {        "name": "Back Reflection Sharpness",        "matchName": "ADBE 3DText Back Gloss",        "valueType": "OneD",        "defaultValue": 100      },      {        "name": "Back Reflection Rolloff",        "matchName": "ADBE 3DText Back Fresnel",        "valueType": "OneD",        "defaultValue": 0      },      {        "name": "Back Transparency",        "matchName": "ADBE 3DText Back Xparency",        "valueType": "OneD",        "defaultValue": 0      },      {        "name": "Back Transparency Rolloff",        "matchName": "ADBE 3DText Back XparRoll",        "valueType": "OneD",        "defaultValue": 0      },      {        "name": "Back Index of Refraction",        "matchName": "ADBE 3DText Back IOR",        "valueType": "OneD",        "defaultValue": 1      },      {        "name": "Bevel Depth",        "matchName": "ADBE 3DText Bevel Depth",        "valueType": "OneD",        "defaultValue": 2      },      {        "name": "Extrusion Depth",        "matchName": "ADBE 3DText Extrude Depth",        "valueType": "OneD",        "defaultValue": 0      },      {        "name": "Stroke Width",        "matchName": "ADBE Text Stroke Width",        "valueType": "OneD",        "defaultValue": 0      },      {        "name": "Line Anchor",        "matchName": "ADBE Text Line Anchor",        "valueType": "OneD",        "defaultValue": 50      },      {        "name": "Tracking Type",        "matchName": "ADBE Text Track Type",        "valueType": "OneD",        "defaultValue": 1      },      {        "name": "Tracking Amount",        "matchName": "ADBE Text Tracking Amount",        "valueType": "OneD",        "defaultValue": 0      },      {        "name": "Character Alignment",        "matchName": "ADBE Text Character Change Type",        "valueType": "OneD",        "defaultValue": 1      },      {        "name": "Character Range",        "matchName": "ADBE Text Character Range",        "valueType": "OneD",        "defaultValue": 1      },      {        "name": "Character Value",        "matchName": "ADBE Text Character Replace",        "valueType": "OneD",        "defaultValue": 0      },      {        "name": "Character Offset",        "matchName": "ADBE Text Character Offset",        "valueType": "OneD",        "defaultValue": 0      },      {        "name": "Line Spacing",        "matchName": "ADBE Text Line Spacing",        "valueType": "TwoD",        "defaultValue": [          0,          0        ]      },      {        "name": "Blur",        "matchName": "ADBE Text Blur",        "valueType": "TwoD",        "defaultValue": [          0,          0        ]      },      {        "name": "",        "matchName": "ADBE Text VF Axis 1",        "valueType": "UNKNOWN_161",        "defaultValue": 0      },      {        "name": "",        "matchName": "ADBE Text VF Axis 2",        "valueType": "UNKNOWN_161",        "defaultValue": 0      },      {        "name": "",        "matchName": "ADBE Text VF Axis 3",        "valueType": "UNKNOWN_161",        "defaultValue": 0      },      {        "name": "",        "matchName": "ADBE Text VF Axis 4",        "valueType": "UNKNOWN_161",        "defaultValue": 0      },      {        "name": "",        "matchName": "ADBE Text VF Axis 5",        "valueType": "UNKNOWN_161",        "defaultValue": 0      },      {        "name": "",        "matchName": "ADBE Text VF Axis 6",        "valueType": "UNKNOWN_161",        "defaultValue": 0      },      {        "name": "",        "matchName": "ADBE Text VF Axis 7",        "valueType": "UNKNOWN_161",        "defaultValue": 0      },      {        "name": "",        "matchName": "ADBE Text VF Axis 8",        "valueType": "UNKNOWN_161",        "defaultValue": 0      }    ]  },  "animatorSelectors": {    "name": "Selectors",    "matchName": "ADBE Text Selectors",    "type": "group",    "numProperties": 0,    "children": [          ]  },  "transform": {    "name": "Transform",    "matchName": "ADBE Transform Group",    "type": "group",    "numProperties": 12,    "children": [      {        "name": "Anchor Point",        "matchName": "ADBE Anchor Point",        "valueType": "ThreeD_SPATIAL",        "defaultValue": [          0,          0,          0        ]      },      {        "name": "Position",        "matchName": "ADBE Position",        "valueType": "ThreeD_SPATIAL",        "defaultValue": [          960,          540,          0        ]      },      {        "name": "X Position",        "matchName": "ADBE Position_0",        "valueType": "OneD",        "defaultValue": 0      },      {        "name": "Y Position",        "matchName": "ADBE Position_1",        "valueType": "OneD",        "defaultValue": 0      },      {        "name": "Z Position",        "matchName": "ADBE Position_2",        "valueType": "OneD",        "defaultValue": 0      },      {        "name": "Scale",        "matchName": "ADBE Scale",        "valueType": "ThreeD",        "defaultValue": [          100,          100,          100        ]      },      {        "name": "Orientation",        "matchName": "ADBE Orientation",        "valueType": "ThreeD_SPATIAL",        "defaultValue": [          0,          0,          0        ]      },      {        "name": "X Rotation",        "matchName": "ADBE Rotate X",        "valueType": "OneD",        "defaultValue": 0      },      {        "name": "Y Rotation",        "matchName": "ADBE Rotate Y",        "valueType": "OneD",        "defaultValue": 0      },      {        "name": "Rotation",        "matchName": "ADBE Rotate Z",        "valueType": "OneD",        "defaultValue": 0      },      {        "name": "Opacity",        "matchName": "ADBE Opacity",        "valueType": "OneD",        "defaultValue": 100      },      {        "name": "Appears in Reflections",        "matchName": "ADBE Envir Appear in Reflect",        "valueType": "OneD",        "defaultValue": 1      }    ]  }}